{"id": 635, "name": "Памятник Петру I и Ф. Лефорту в Лефортове (Москва)", "location": "Москва, сквер на углу Красноказарменной и Волочаевской улиц (м. «Авиамоторная»)", "type": "Памятник монументального искусства", "status": "Памятник федерального значения", "description": "Памятник «Пётр I и Франц Лефорт» открыт 23 сентября 1999 года в ознаменование 300-летия исторического района Лефортово. Установлен в главного входа в Лефортовский парк.\nВ конце XVII века Пётр I поручил Францу Лефорту устройство солдатского поселения на левом берегу Яузы, против Немецкой слободы. Эту местность вскоре стали называть по имени сподвижника царя. 300-летний юбилей местности отсчитывался от времени строительства Лефортовского дворца.\nПамятник-обелиск из розового гранита высотой 8 м имеет форму прямой призмы с квадратом в основании и завершением в форме правильной пирамиды, увенчанной бронзовой фигуркой крылатого льва. На одной из граней пирамиды в нише размещён бронзовый горельеф, изображающий Петра I и Франца Лефорта, облачённых в воинские доспехи. В основании горельефа надпись: «ПЕТР I ФРАНЦ ЛЕФОРТ». В нишах других граней обелиска помещены бронзовые горельефы с изображением атрибутов воинской славы и символов петровской эпохи, а также рельефный картуш с текстом: «Памятный знак / сооружен в ознаменование / 300-летия Лефортова / посвящен императору России / Петру Великому / и его сподвижнику / Францу Лефорту / по проекту архитекторов / Кочергина В. В. Алешиной В. В. / скульпторов Суровцева В. А.  / Суровцева Д. В. Суровцевой Е. М.»\n\nЛефортово // Москва: Энциклопедия / гл. ред. С. О  Шмидт, сост. М. И. Андреев, В. М. Карев. М., 1998. С. 434.\n", "imageURLs": ["http://petersmonuments.ru/upload/iblock/585/585be7f5f2ac9d37316f968e5cc598ae.jpg", "http://petersmonuments.ru/upload/iblock/1e9/1e91020e29840431875300aadc875030.jpg", "http://petersmonuments.ru/upload/iblock/7bd/7bd80744d60a66c04aacd5a1d3bd7eeb.jpg"]}