{"id": 839, "name": "Дом с палатами А. Т. Ржевского (Москва)", "location": "Москва, Пречистенка, 10 (м. «Кропоткинская»)", "type": "Памятник гражданской архитектуры", "status": "", "description": "Среди последующих владельцев дома выделяются потомственная почетная гражданка, благотворительница Вера Александровна Хлудова и купец Мориц Филипп, учителем сына которого был Б. Л. Пастернак, живший здесь же в 1915 году. В том же году дом Филиппа подвергся немецкому погрому, и хозяева переехал в съемную квартиру.\nВ первые советские годы усадьба сохранила жилую функцию как «Дом коммуны московского округа связи». В 1942–1948 годах в главном доме располагался Еврейский антифашистский комитет (мемориальная доска), затем и до сих пор – Международная ассоциация Фонда мира и Комитет за мир и сотрудничество.\nПамятники архитектур Москвы. Земляной город. М., 1989. С. 60.\n", "imageURLs": ["http://petersmonuments.ru/upload/iblock/fcf/fcfedcf0fad1b707ddfa8b095dedf7d1.jpg", "http://petersmonuments.ru/upload/iblock/5f5/5f5a40fb3e9864847d159a2c5a4f53a4.jpg"]}